[
  {
    "id": "my-adulthood",
    "name": "Adulthood",
    "description": "Adulthood",
    "category": "illustration",
    "mainImage": {
      "link": "Illustration/1 Childish Realism.png",
      "description": "Adulthood",
      "isBig": true
    },
    "images": [
      {
        "link": "Illustration/1 Childish Realism/1 Airport.png",
        "description": "Airport"
      },
      {
        "link": "Illustration/1 Childish Realism/2 Rainy.png",
        "description": "Rainy"
      },
      {
        "link": "Illustration/1 Childish Realism/3 Park.png",
        "description": "Park"
      },
      {
        "link": "Illustration/1 Childish Realism/4 Room.png",
        "description": "Room"
      },
      {
        "link": "Illustration/1 Childish Realism/5 Market.png",
        "description": "Market"
      },
      {
        "link": "Illustration/1 Childish Realism/6 Love.png",
        "description": "Love"
      }
    ]
  },
  {
    "id": "mixed-media",
    "name": "Mixed Media",
    "description": "Mixed Media",
    "category": "illustration",
    "mainImage":
      {
        "link": "Illustration/Mixed-Media/seal.jpg",
        "description": "Mixed-Media"
      },
    "images": [
      {
        "link": "Illustration/Mixed-Media/seal.jpg",
        "description": "Seal",
        "height": 420
      },
      {
        "link": "Illustration/Mixed-Media/dogs.jpg",
        "description": "Dogs",
        "height": 420
      },
      {
        "link": "Illustration/Mixed-Media/strawberry-cat.jpg",
        "description": "Strawberry Cat",
        "height": 420
      }
    ]
  },
  {
    "id": "colored-pencil",
    "name": "Colored Pencil",
    "description": "Colored Pencil",
    "category": "illustration",
    "mainImage":
    {
      "link": "Illustration/3 Colored Pencils.png",
      "description": "Colored Pencils"
    },
    "images": [
      {
        "link": "Illustration/3 Colored Pencils.png",
        "description": "Colored Pencils"
      }
    ]
  },
  {
    "id": "collage",
    "name": "Collage",
    "description": "Collage",
    "category": "illustration",
    "mainImage": {
      "link": "Illustration/6 Collage.png",
      "description": "Collage"
    },
    "images": [
      {
        "link": "Illustration/6 Collage.png",
        "description": "Collage"
      }
    ]
  },
  {
    "id": "acrylic-painting",
    "name": "Acrylic Painting",
    "description": "Acrylic Painting",
    "category": "illustration",
    "mainImage":
      {
        "link": "Illustration/5 Acrylic Painting.png",
        "description": "Acrylic Painting"
      },
    "images": [
      {
        "link": "Illustration/5 Acrylic Painting.png",
        "description": "Acrylic Painting"
      }
    ]
  },



  {
    "id": "zahava",
    "name": "Zahava",
    "description": "Zahava is the best",
    "category": "branding",
    "overlayBackgroundColor": "cf8c84",
    "overlayTextColor": "ffffff",
    "mainImage":
    {
      "link": "Branding/2 Zahava/01 Cover Zahava.jpg",
      "isBig": true
    },
    "images": [
      {
        "link": "Branding/2 Zahava/01 Cover Zahava.jpg"
      },
      {
        "link": "Branding/2 Zahava/02 Booklet.jpg"
      },
      { "link": "Branding/2 Zahava/03 Open Booklet.jpg" },
      { "link": "Branding/2 Zahava/04 Cards.jpg" },
      {
        "link": "Branding/2 Zahava/05 Jewelry.jpg"
      },
      { "link": "Branding/2 Zahava/06 Brochure.jpg" },
      { "link": "Branding/2 Zahava/07 Business Card.jpg" },
      {
        "link": "Branding/2 Zahava/08 Matchbox.jpg"
      },
      {
        "link": "Branding/2 Zahava/09 Computer & Mobile.jpg"
      },
      {
        "link": "Branding/2 Zahava/10 Mobile.jpg"
      },
      {
        "link": "Branding/2 Zahava/11 Computer.jpg"
      },
      {
        "link": "Branding/2 Zahava/12 Photo1.jpg"
      },
      {
        "link": "Branding/2 Zahava/13 Photo2.jpg"
      },
      {
        "link": "Branding/2 Zahava/14 Photo3.jpg"
      },
      {
        "link": "Branding/2 Zahava/15 Photo4.jpg"
      },
      {
        "link": "Branding/2 Zahava/16 Photo5.jpg"
      }
    ]
  },
  {
    "id": "events-invitations",
    "name": "Invitations",
    "description": "Invitations are fun",
    "category": "branding",
    "overlayBackgroundColor": "fefaee ",
    "overlayTextColor": "815c58)",
    "mainImage": {
      "link": "Branding/5 Events Invitations/Events.jpg"
    },
    "images": [
      {"link": "Branding/5 Events Invitations/01 cover events.jpg"},
      {"link": "Branding/5 Events Invitations/02 Dana Wedding.jpg"},
      {"link": "Branding/5 Events Invitations/03 Tali Wedding.jpg"}
    ]
  },
  {
    "id": "popland",
    "name": "Popland",
    "description": "Popland",
    "game": true,
    "category": "branding",
    "overlayBackgroundColor": "f2f2f2",
    "overlayTextColor": "815c58",
    "mainImage": {
      "link": "Branding/1 Popland/Popland.jpg",
      "description": "Popland"
    },
    "images": [
      {
        "link": "Branding/1 Popland/01 Popland Cover.jpg"
      },
      {
        "link": "Branding/1 Popland/02 Popland Logo.jpg"
      },
      {
        "link": "Branding/1 Popland/03 Popland Characters.jpg"
      },
      {
        "link": "Branding/1 Popland/04 Popland Bad Characters.jpg"
      },
      {
        "link": "Branding/1 Popland/05 Popland 50s.jpg"
      },
      {
        "link": "Branding/1 Popland/06 Popland 60s.jpg"
      },
      {
        "link": "Branding/1 Popland/07 Popland 70s.jpg"
      },
      {
        "link": "Branding/1 Popland/08 Popland 80s.jpg"
      }
    ]
  },
  {
    "id": "pondicherie",
    "name": "Pondichérie",
    "description": "Pondichérie",
    "game": false,
    "category": "branding",
    "overlayBackgroundColor": "a2a394",
    "overlayTextColor": "ffffff",
    "mainImage": {
      "link": "Branding/3 Pondicherie/Pondicherie.jpg",
      "description": "Pondichérie"
    },
    "images": [
      {
        "link": "Branding/3 Pondicherie/01 Cover Pondicherie.jpg"
      },
      {
        "link": "Branding/3 Pondicherie/02 Print.jpg"
      },
      {
        "images": [
          {
            "link": "Branding/3 Pondicherie/03 Magazine Cover.jpg"
          },
          {
            "link": "Branding/3 Pondicherie/04 Open Magazine.jpg"
          }
        ]
      },
      {
        "link": "Branding/3 Pondicherie/05 Flyer.jpg",
        "description": ""
      }
    ]
  },
  {
    "id": "tulerie",
    "name": "Tulerie",
    "description": "Tulerie",
    "game": false,
    "category": "branding",
    "overlayBackgroundColor": "f1eae4",
    "overlayTextColor": "815c58",
    "mainImage": {
      "link": "Branding/Tulerie/Tulerie.jpg",
      "description": "The Brave Collection"
    },
    "images": [
      {
        "link": "Branding/Tulerie/01 Cover tulerie.jpg"
      },
      {
        "link": "Branding/Tulerie/02 Three Mobiles.jpg"
      },
      {
        "link": "Branding/Tulerie/03 Computer Tulerie.jpg"
      }
    ]
  }
]


